hr_platform/__init__.py
hr_platform/async_client.py
hr_platform/client.py
hr_platform/exceptions.py
hr_platform/py.typed
hr_platform/core/__init__.py
hr_platform/core/async_http.py
hr_platform/core/config.py
hr_platform/core/http.py
hr_platform/models/__init__.py
hr_platform/models/admin.py
hr_platform/models/analytics.py
hr_platform/models/compliance.py
hr_platform/models/enums.py
hr_platform/models/records.py
hr_platform/models/users.py
hr_platform/models/webhooks.py
hr_platform/resources/__init__.py
hr_platform/resources/admin.py
hr_platform/resources/analytics.py
hr_platform/resources/base.py
hr_platform/resources/compliance.py
hr_platform/resources/records.py
hr_platform/resources/users.py
hr_platform/resources/webhooks.py
hr_platform/utils/__init__.py
hr_platform/utils/pandas_helpers.py
hr_platform_sdk-0.1.0.dist-info/METADATA
hr_platform_sdk-0.1.0.dist-info/WHEEL
hr_platform_sdk-0.1.0.dist-info/RECORD
