Metadata-Version: 2.4
Name: hr-platform-sdk
Version: 0.1.0
Summary: Python SDK for HR Platform API - Type-safe access with async support and pandas integration
Project-URL: Homepage, https://github.com/vollers-group/hr-platform
Project-URL: Documentation, https://github.com/vollers-group/hr-platform/tree/main/packages/sdk-python
Project-URL: Repository, https://github.com/vollers-group/hr-platform
Project-URL: Changelog, https://github.com/vollers-group/hr-platform/blob/main/packages/sdk-python/CHANGELOG.md
Project-URL: Bug Tracker, https://github.com/vollers-group/hr-platform/issues
Author-email: Vollers Group IT <it@vollers.de>
License-Expression: MIT
Keywords: analytics,api,hr,hr-platform,httpx,pydantic,sdk
Classifier: Development Status :: 4 - Beta
Classifier: Intended Audience :: Developers
Classifier: License :: OSI Approved :: MIT License
Classifier: Operating System :: OS Independent
Classifier: Programming Language :: Python :: 3
Classifier: Programming Language :: Python :: 3.9
Classifier: Programming Language :: Python :: 3.10
Classifier: Programming Language :: Python :: 3.11
Classifier: Programming Language :: Python :: 3.12
Classifier: Topic :: Office/Business :: Financial :: Accounting
Classifier: Topic :: Software Development :: Libraries :: Python Modules
Classifier: Typing :: Typed
Requires-Python: >=3.9
Requires-Dist: httpx>=0.27.0
Requires-Dist: pydantic>=2.0.0
Provides-Extra: all
Requires-Dist: datamodel-code-generator>=0.25.0; extra == 'all'
Requires-Dist: mypy>=1.0.0; extra == 'all'
Requires-Dist: pandas-stubs>=2.0.0; extra == 'all'
Requires-Dist: pandas>=2.0.0; extra == 'all'
Requires-Dist: pytest-asyncio>=0.23.0; extra == 'all'
Requires-Dist: pytest-cov>=4.0.0; extra == 'all'
Requires-Dist: pytest-httpx>=0.30.0; extra == 'all'
Requires-Dist: pytest>=8.0.0; extra == 'all'
Requires-Dist: ruff>=0.3.0; extra == 'all'
Provides-Extra: codegen
Requires-Dist: datamodel-code-generator>=0.25.0; extra == 'codegen'
Provides-Extra: dev
Requires-Dist: mypy>=1.0.0; extra == 'dev'
Requires-Dist: pandas-stubs>=2.0.0; extra == 'dev'
Requires-Dist: pandas>=2.0.0; extra == 'dev'
Requires-Dist: pytest-asyncio>=0.23.0; extra == 'dev'
Requires-Dist: pytest-cov>=4.0.0; extra == 'dev'
Requires-Dist: pytest-httpx>=0.30.0; extra == 'dev'
Requires-Dist: pytest>=8.0.0; extra == 'dev'
Requires-Dist: ruff>=0.3.0; extra == 'dev'
Provides-Extra: pandas
Requires-Dist: pandas>=2.0.0; extra == 'pandas'
